Hw01/design.sv
// Code your design here
module decoder_2_4(E , In , Out);    
input E;                                 //宣告致能輸入E
input [1:0] In;                          //宣告In[0]、In[1]輸入
output [3:0] Out;                        //宣告Out[0]~Out[3]輸出
wire [3:0] Out;                          //宣告Out[0]~Out[3]為連接線
assign Out = E ? 1'b1 << In : 4'h0;      //E為1時輸出二進制左移In個位元，為0時輸出0
endmodule

module decoder_3_8(E , In , Out);
input E;                                 //宣告致能輸入E
input [2:0] In;                          //宣告In[0]~In[2]輸入
output [7:0] Out;                        //宣告Out[0]~Out[7]輸出
wire E1 , G1 , G2;                       //宣告三對八解碼器致能線E1，二對四解碼器致能線G1、G2
not u1(E1 , In[2]);                      //E1=透過NOT閘連接E1與In[2]
and a1(G1 , E , In[2]);                  //G1=透過AND閘連接E與In[2]
and a2(G2 , E , E1);                     //G2=透過AND閘連接E與E2
decoder_2_4 block1(G1 , In[1 : 0] , Out[7 : 4]); //Out[7:4] = G1及In0[0:1]輸入decoder_2_4
decoder_2_4 block2(G2 , In[1 : 0] , Out[3 : 0]); //Out[7:4] = G1及In0[0:1]輸入decoder_2_4
endmodule

module clkgen(clka, clkb, clka_out, clkb_out);
input clka, clkb;                                //宣告clka、clkb輸入埠
output clka_out, clkb_out;                       //宣告clka_out、clkb_out輸出埠
reg clka_out, clkb_out;                          //將clka_out、clkb_out連接暫存器
always @(clka) begin                             //當clka有變化時 clka_out = clka
clka_out = clka;
end
always @(clkb) begin                             //當clkb有變化時 clkb_out = clkb
clkb_out = clkb;
end
endmodule

Hw01/testbench.sv
// Code your testbench here
// or browse Examples
module decoder_3_8_tb;
reg E_tb;                                        //宣告暫存器E_tb
reg clka,clkb;                                  //宣告暫存器clka、clkb
reg [2:0] In_tb;                                 //宣告暫存器In_tb[0]~In_tb[2]
wire [7:0] Out_tb;                               //宣告暫存器Out_tb[0]~Out_tb[7]
wire clka_out, clkb_out;                         //宣告連接線clka_out、clkb_out
decoder_3_8 decoder_1(.E(E_tb), .In(In_tb), .Out(Out_tb));//宣告decoder_1為三對八解碼器並傳入變數(致能輸入、輸入、輸出)
clkgen clkgen_1(.clka(clka), .clkb(clkb), .clka_out(clka_out), .clkb_out(clkb_out));//宣告clkgen_1為時脈產生器並傳入變數(時脈產生A輸入及輸出、時脈產生B輸入及輸出)
initial begin                                    //在一開始初始化的時後，可以透過 initial 設定初值
clka = 1'b0; clkb = 1'b0;                        //預設clka、clkb為1位元的0
end
always begin                                     
#10 clka = ~clka;                                //延遲10秒後clka=NOT(clka)
end
always begin
#20 clkb = ~clkb;                                //延遲10秒後clkb=NOT(clkb)
end
    
initial begin                                    
#0 E_tb = 0; In_tb = 3'b000;                     //預設致能為0，三個輸入為000
#10 E_tb = 1; In_tb = 3'b000;                    //延遲10後致能為1，三個輸入為000
#10 E_tb = 1; In_tb = 3'b001;                    //延遲10後致能為1，三個輸入為001
#10 E_tb = 1; In_tb = 3'b010;                    //延遲10後致能為1，三個輸入為010
#10 E_tb = 1; In_tb = 3'b011;                    //延遲10後致能為1，三個輸入為011
#10 E_tb = 1; In_tb = 3'b100;                    //延遲10後致能為1，三個輸入為100
#10 E_tb = 1; In_tb = 3'b101;                    //延遲10後致能為1，三個輸入為101
#10 E_tb = 1; In_tb = 3'b110;                    //延遲10後致能為1，三個輸入為110
#10 E_tb = 1; In_tb = 3'b111;                    //延遲10後致能為1，三個輸入為111
#10 $finish;
end
initial begin
$dumpfile("decoder.vcd");                        //將輸出訊號紀錄到decoder.vcd
$dumpvars(0, decoder_1);                         //紀錄decoder_1產生的訊號
$dumpvars(0, clkgen_1);                          //紀錄clkgen_1產生的訊號                                    
end
endmodule

Hw01/decoder.vcd
$date
	Sat Mar 26 14:51:16 2022
$end
$version
	Icarus Verilog
$end
$timescale
	1s
$end
$scope module decoder_3_8_tb $end
$scope module decoder_1 $end
$var wire 1 ! E $end
$var wire 1 " E1 $end
$var wire 1 # G1 $end
$var wire 1 $ G2 $end
$var wire 3 % In [2:0] $end
$var wire 8 & Out [7:0] $end
$scope module block1 $end
$var wire 1 # E $end
$var wire 2 ' In [1:0] $end
$var wire 4 ( Out [3:0] $end
$upscope $end
$scope module block2 $end
$var wire 1 $ E $end
$var wire 2 ) In [1:0] $end
$var wire 4 * Out [3:0] $end
$upscope $end
$upscope $end
$upscope $end
$scope module decoder_3_8_tb $end
$scope module clkgen_1 $end
$var wire 1 + clka $end
$var wire 1 , clkb $end
$var reg 1 - clka_out $end
$var reg 1 . clkb_out $end
$upscope $end
$upscope $end
$enddefinitions $end
#0
$dumpvars
0.
0-
0,
0+
b0 *
b0 )
b0 (
b0 '
b0 &
b0 %
0$
0#
1"
0!
$end
#10
b1 &
b1 *
1$
1-
1!
1+
#20
b10 &
b10 *
b1 '
b1 )
0-
1.
b1 %
0+
1,
#30
b100 &
b100 *
b10 '
b10 )
1-
b10 %
1+
#40
b1000 &
b1000 *
b11 '
b11 )
0-
0.
b11 %
0+
0,
#50
0$
b1 (
0"
1#
b10000 &
b0 *
b0 '
b0 )
1-
b100 %
1+
#60
b100000 &
b10 (
b1 '
b1 )
0-
1.
b101 %
0+
1,
#70
b1000000 &
b100 (
b10 '
b10 )
1-
b110 %
1+
#80
b10000000 &
b1000 (
b11 '
b11 )
0-
0.
b111 %
0+
0,
